selectel_cloud_api
