Metadata-Version: 1.1
Name: selectel-cloud-api
Version: 1.1
Summary: api select cloud api
Home-page: https://github.com/RustoriaRu/SelectelCloudApi
Author: vir-mir
Author-email: virmir49@gmail.com
License: MIT
Keywords: selectel.ru selectel api,cloud
Platform: UNKNOWN
Classifier: Environment :: Web Environment
Classifier: Intended Audience :: Developers
Classifier: License :: OSI Approved :: MIT License
Classifier: Programming Language :: Python :: 2.7
Classifier: Programming Language :: Python :: 3.3
Classifier: Programming Language :: Python :: 3.4
Classifier: Topic :: Software Development :: Libraries :: Python Modules
